_Sailfish.cpython-310-x86_64-linux-gnu.so
msasim.libs/libstdc++-a9383cce.so.6.0.28
msasim.libs/libgcc_s-a04fdf82.so.1
msasim/__init__.py
msasim/sailfish.py
msasim-2024.5.221255.dist-info/WHEEL
msasim-2024.5.221255.dist-info/LICENSE
msasim-2024.5.221255.dist-info/top_level.txt
msasim-2024.5.221255.dist-info/RECORD
msasim-2024.5.221255.dist-info/METADATA
