Metadata-Version: 2.1
Name: msasim
Version: 2024.5.221255
Summary: A fast MSA simulator
Home-page: https://github.com/elyawy/Sailfish-backend
Author: Elya Wygoda
Author-email: elya.wygoda@gmail.com
Requires-Python: >=3.6
License-File: LICENSE
Provides-Extra: test
Requires-Dist: pytest ; extra == 'test'
